i24-2.1.0.dist-info/METADATA
i24-2.1.0.dist-info/WHEEL
i24/__init__.py
i24/i24.cp313-win_amd64.pyd
i24-2.1.0.dist-info/RECORD
