Metadata-Version: 2.4
Name: i24
Version: 2.1.0
Summary: A Rust library for working with 24-bit integers.
License: MIT
Project-URL: Source Code, https://github.com/jmg049/i24
